rc_cli/__init__.py
rc_cli/alias_handler.py
rc_cli/client.py
rc_cli/config.py
rc_cli/emoji.py
rc_cli/logger.py
rc_cli/phase.py
rc_cli/add_grader/__init__.py
rc_cli/add_grader/add_grader.py
rc_cli/assignment_deploy/__init__.py
rc_cli/assignment_deploy/assignment_deployer.py
rc_cli/assignment_seeder/__init__.py
rc_cli/assignment_seeder/assignment_seeder.py
rc_cli/builder/__init__.py
rc_cli/builder/builder.py
rc_cli/deploy/__init__.py
rc_cli/deploy/deployer.py
rc_cli/error_catcher/__init__.py
rc_cli/error_catcher/error_catcher.py
rc_cli/gitlab/__init__.py
rc_cli/gitlab/groups_api.py
rc_cli/gitlab/projects_api.py
rc_cli/gitlab/users_api.py
rc_cli/group_deleter/__init__.py
rc_cli/group_deleter/group_deleter.py
rc_cli/init/__init__.py
rc_cli/init/initializer.py
rc_cli/ninja_patch/__init__.py
rc_cli/ninja_patch/ninja_patcher.py
rc_cli/restore/__init__.py
rc_cli/restore/restorer.py
rc_cli/tests/__init__.py
rc_cli/tests/assignment_seeder_tests.py
rc_cli/tests/copy_test.py
rc_cli/tests/initializer_tests.py
rc_cli/tests/restorer_tests.py
rc_cli/utils/__init__.py
rc_cli/utils/context_extractor.py
rc_cli/utils/copier.py
rc_cli/utils/git_alias_handler.py
rc_cli/utils/git_wrapper.py
rc_cli/utils/pinger.py
rc_cli/utils/remover.py
rc_cli-0.4.1.dist-info/METADATA
rc_cli-0.4.1.dist-info/RECORD
rc_cli-0.4.1.dist-info/WHEEL
rc_cli-0.4.1.dist-info/entry_points.txt
rc_cli-0.4.1.dist-info/top_level.txt
