Metadata-Version: 2.1
Name: rc-cli
Version: 0.4.1
Summary: RoseCloud CLI
Home-page: UNKNOWN
Author: RoseCloud Team
Author-email: rupakhet@rose-hulman.edu
License: MIT
Project-URL: Bug Reports, https://ada.csse.rose-hulman.edu/RoseBuild/rc-cli/boards
Project-URL: Source, https://ada.csse.rose-hulman.edu/RoseBuild/rc-cli/tree/master
Keywords: rose-hulman rosecloud management setuptools
Platform: UNKNOWN
Classifier: Development Status :: 3 - Alpha
Classifier: Environment :: Console
Classifier: Intended Audience :: Education
Classifier: License :: OSI Approved :: MIT License
Classifier: Natural Language :: English
Classifier: Operating System :: MacOS :: MacOS X
Classifier: Operating System :: Microsoft :: Windows
Classifier: Operating System :: POSIX :: Linux
Classifier: Programming Language :: Python :: 3 :: Only
Classifier: Programming Language :: Python :: 3.5
Classifier: Programming Language :: Python :: 3.6
Classifier: Programming Language :: Python :: 3.7
Classifier: Topic :: Education
Classifier: Topic :: Software Development :: Version Control :: Git
Classifier: Topic :: System :: Filesystems
Classifier: Topic :: Utilities
Requires-Python: >=3.5
Requires-Dist: Click (==6.7)
Requires-Dist: colorama (==0.3.9)
Requires-Dist: requests (==2.18.4)
Requires-Dist: gitpython (==2.1.9)
Requires-Dist: pytz (==2018.3)
